youtrack/__init__.py
youtrack/auth.py
youtrack/exceptions.py
youtrack/models.py
youtrack_rest_api-0.0.1.dist-info/DESCRIPTION.rst
youtrack_rest_api-0.0.1.dist-info/METADATA
youtrack_rest_api-0.0.1.dist-info/RECORD
youtrack_rest_api-0.0.1.dist-info/WHEEL
youtrack_rest_api-0.0.1.dist-info/metadata.json
youtrack_rest_api-0.0.1.dist-info/top_level.txt
