Metadata-Version: 2.0
Name: youtrack-rest-api
Version: 0.0.1
Summary: YouTrack JSON REST API Python 3 Client Library
Home-page: https://github.com/DeKaN/youtrack-rest-api
Author: DeKaN (dekanszn@gmail.com)
Author-email: dekanszn@gmail.com
License: Apache 2.0
Platform: UNKNOWN
Classifier: Development Status :: 3 - Alpha
Classifier: Intended Audience :: Developers
Classifier: License :: OSI Approved :: Apache Software License
Classifier: Operating System :: OS Independent
Classifier: Programming Language :: Python :: 3
Classifier: Programming Language :: Python :: 3.4
Classifier: Programming Language :: Python :: 3.5
Classifier: Programming Language :: Python :: 3.6
Classifier: Topic :: Software Development :: Libraries
Requires-Dist: requests (>=2.13.0)
